setup.cfg
setup.py
alacarte/__init__.py
alacarte/core.py
alacarte/engines.py
alacarte/release.py
alacarte/resolver.py
alacarte/util.py
alacarte/serialize/__init__.py
alacarte/template/__init__.py
cti/__init__.py
cti/core.py
cti/engines.py
cti/middleware.py
cti/release.py
cti/resolver.py
cti/serializers/__init__.py
cti/templating/__init__.py
marrow/__init__.py
marrow.templating.egg-info/PKG-INFO
marrow.templating.egg-info/SOURCES.txt
marrow.templating.egg-info/dependency_links.txt
marrow.templating.egg-info/entry_points.txt
marrow.templating.egg-info/namespace_packages.txt
marrow.templating.egg-info/top_level.txt
marrow.templating.egg-info/zip-safe
marrow/templating/__init__.py
marrow/templating/core.py
marrow/templating/engines.py
marrow/templating/release.py
marrow/templating/resolver.py
marrow/templating/util.py
marrow/templating/serialize/__init__.py
marrow/templating/serialize/bencode.py
marrow/templating/serialize/json.py
marrow/templating/serialize/marshal.py
marrow/templating/serialize/pickle.py
marrow/templating/serialize/yaml.py
marrow/templating/template/__init__.py
marrow/templating/template/cheetah.py
marrow/templating/template/engine.py
marrow/templating/template/formatter.py
marrow/templating/template/genshi.py
marrow/templating/template/jinja2.py
marrow/templating/template/kajiki.py
marrow/templating/template/mako.py
marrow/templating/template/sprintf.py
marrow/templating/template/template.py