Metadata-Version: 1.0
Name: marrow.templating
Version: 1.0.2
Summary: A common templating and serialization interface for Python applications.
Home-page: https://github.com/marrow/marrow.templating
Author: Alice Bevan-McGregor
Author-email: alice+marrow@gothcandy.com
License: MIT
Platform: UNKNOWN
Classifier: Development Status :: 5 - Production/Stable
Classifier: Environment :: Console
Classifier: Intended Audience :: Developers
Classifier: License :: OSI Approved :: MIT License
Classifier: Operating System :: OS Independent
Classifier: Programming Language :: Python
Classifier: Topic :: Software Development :: Libraries :: Python Modules
